{
  "resState": [
    {
      "md5": "5347ed1c51a420355c604b95a1c870e4",
      "fileName": "42.png",
      "lastTime": 1589513434572,
      "useTimes": 1
    },
    {
      "md5": "118583da9ee94c9afdd965a382d38e56",
      "fileName": "43.png",
      "lastTime": 0,
      "useTimes": 0
    },
    {
      "md5": "74e499b6f836089fd37e460bd7f22afb",
      "fileName": "50.png",
      "lastTime": 1589370813748,
      "useTimes": 0
    },
    {
      "md5": "6e884950e79f0f83bbf1941e9aef942b",
      "fileName": "49.png",
      "lastTime": 0,
      "useTimes": 0
    },
    {
      "md5": "5df24ec33fef1e667755b1061158999d",
      "fileName": "47.png",
      "lastTime": 0,
      "useTimes": 0
    },
    {
      "md5": "0eda91e3bc7a769ec2ea347ef4725063",
      "fileName": "41.png",
      "lastTime": 0,
      "useTimes": 0
    },
    {
      "md5": "0b582e784f6a9203399f8b27a88b4d6f",
      "fileName": "48.png",
      "lastTime": 1589370813743,
      "useTimes": 0
    },
    {
      "md5": "04e14e37bcc5a47316e533646aeac6a1",
      "fileName": "45.png",
      "lastTime": 1589370813735,
      "useTimes": 0
    },
    {
      "md5": "bd49a1ec8fa1968a3f7c96864369e9ef",
      "fileName": "46.png",
      "lastTime": 0,
      "useTimes": 0
    },
    {
      "md5": "a600698a4aec446a891d851c6ddc2fd3",
      "fileName": "44.png",
      "lastTime": 1589370813827,
      "useTimes": 1
    },
    {
      "md5": "76c5ab32808741b31ccd2dc628947957",
      "fileName": "40.png",
      "lastTime": 1589447287014,
      "useTimes": 1
    }
  ],
  "canUseCount": 19,
  "archiveTimes": 0,
  "componentResNamePath": "Arts/style_Other/change/role"
}